odoo/addons/partner_country_state_required/README.rst
odoo/addons/partner_country_state_required/__init__.py
odoo/addons/partner_country_state_required/__manifest__.py
odoo/addons/partner_country_state_required/hooks.py
odoo/addons/partner_country_state_required/i18n/it.po
odoo/addons/partner_country_state_required/i18n/partner_country_state_required.pot
odoo/addons/partner_country_state_required/models/__init__.py
odoo/addons/partner_country_state_required/models/res_partner.py
odoo/addons/partner_country_state_required/readme/CONTRIBUTORS.rst
odoo/addons/partner_country_state_required/readme/DESCRIPTION.rst
odoo/addons/partner_country_state_required/static/description/icon.png
odoo/addons/partner_country_state_required/static/description/index.html
odoo/addons/partner_country_state_required/tests/__init__.py
odoo/addons/partner_country_state_required/tests/test_state_required.py
odoo_addon_partner_country_state_required-16.0.1.0.0.4.dist-info/METADATA
odoo_addon_partner_country_state_required-16.0.1.0.0.4.dist-info/WHEEL
odoo_addon_partner_country_state_required-16.0.1.0.0.4.dist-info/top_level.txt
odoo_addon_partner_country_state_required-16.0.1.0.0.4.dist-info/RECORD
